{
  "title": "People: society",
  "chapters": [
    {
      "number": "1",
      "title": "Introduction",
      "pages": "1-46",
      "author": "Ross, M. and Pawley, A. and Osmond, M."
    },
    {
      "number": "2",
      "title": "Kinship",
      "pages": "47-140",
      "author": "Malcolm Ross and Jeffrey C. Marck"
    },
    {
      "number": "3",
      "title": "Was Proto Oceanic society matrilineal?",
      "pages": "141-150",
      "author": "Per Hage"
    },
    {
      "number": "4",
      "title": "Social rank and lunations",
      "pages": "151-174",
      "author": "Andrew Pawley"
    },
    {
      "number": "5",
      "title": "Settlement patterns and territory in the Proto Oceanic speech community",
      "pages": "175-194",
      "author": "Andrew Pawley and Roger Green"
    },
    {
      "number": "6",
      "title": "Recreation: Music, song, dance, games",
      "pages": "195-234",
      "author": "Meredith Osmond"
    },
    {
      "number": "7",
      "title": "The spirit world",
      "pages": "235-248",
      "author": "Meredith Osmond"
    },
    {
      "number": "8",
      "title": "Magic and the supernatural",
      "pages": "249-268",
      "author": "Meredith Osmond"
    },
    {
      "number": "9",
      "title": "Mana",
      "pages": "269-282",
      "author": "Meredith Osmond"
    },
    {
      "number": "10",
      "title": "Tabu",
      "pages": "283-296",
      "author": "Meredith Osmond"
    },
    {
      "number": "11",
      "title": "Seasonal cycles and lunations",
      "pages": "297-368",
      "author": "Meredith Osmond and Malcolm Ross"
    },
    {
      "number": "12",
      "title": "Talking about speaking",
      "pages": "369-402",
      "author": "Malcolm Ross and Bethwyn Evans and Meredith Osmond"
    },
    {
      "number": "13",
      "title": "Trade, exchange, distribution and transfer of possession",
      "pages": "403-426",
      "author": "Meredith Osmond and Malcolm Ross"
    },
    {
      "number": "14",
      "title": "Counting: Numerals and numeral classifiers",
      "pages": "427-514",
      "author": "Malcolm Ross"
    },
    {
      "number": "15",
      "title": "Digit tallying",
      "pages": "515-548",
      "author": "Malcolm Ross"
    },
    {
      "number": "16",
      "title": "Linear measurement",
      "pages": "549-568",
      "author": "Malcolm Ross"
    }
  ]
}